{
  "type": "FeatureCollection",
  "features": [
    {
      "type": "Feature",
      "geometry": {
        "type": "Point",
        "coordinates": [
          114.25539072883544,
          30.615665383366924
        ]
      },
      "properties": {
        "title": "汉口火车站"
      }
    }
  ]
}